{
  "texts": [

            {
            "id": 1,
            "from": "10655111",
            "body": "8月5日 星期五",
            "time": "2016-08-05 12:41"
            },
            {
            "id": 2,
            "from": "95588",
            "body": "您尾号5571卡8月4日10:36POS支出19.96元",
            "time": "2016-08-04 10:40"
            },
            {
            "id": 3,
            "from": "10-6553508",
            "body": "联通阅读 盛夏领红包啦！",
            "time": "2016-07-28 14:13"
            },
            {
            "id": 4,
            "from": "10690404100231",
            "body": "大麦网 验证码：894346，序号：1，切勿泄露!",
            "time": "2016-07-20 16:39"
            },
            {
           "id": 5,
            "from": "10010",
            "body": "尊敬的用户，您好！截止8月8日9时，您本月套餐使用情况如下",
            "time": "2016-08-08 10:11"
            },
            {
            "id": 6,
            "from": "10690188016696",
            "body": "尊敬的c,yz，您的验证码为c42572,如有疑问请联系0527-80878888",
            "time": "2016-08-05 11:26"
            },
            {
            "id": 7,
            "from": "1069077073163",
            "body": "秋季全程班 老学员回馈，基础+强化+冲刺",
            "time": "2016-08-02 11:56"
            },
            {
            "id": 8,
            "from": "1065581605201",
            "body": "联通高校联盟 关注微信公众号 联通高校联盟",
            "time": "2016-07-27 11:18"
            },
            {
            "id": 9,
            "from": "1069-329013111",
            "body": "您的短信验证码是：9604 验证码有效期为5分钟",
            "time": "2016-07-16 23:29"
            },
            {
            "id": 10,
            "from": "106550779112332",
            "body": "淘票票 2016-7-17 15:00金逸影城武汉销品茂IMAX点6号厅《大鱼海棠》已购票成功",
            "time": "2016-07-17 12:43"
            },
    ]
}